python_backtesting_engine/__init__.py
python_backtesting_engine/__main__.py
python_backtesting_engine/window_dialog.py
python_backtesting_engine/Backtesting/Backtester.py
python_backtesting_engine/Backtesting/StratFile.py
python_backtesting_engine/Backtesting/__init__.py
python_backtesting_engine/Brownian_Motion/BrownianMotion.py
python_backtesting_engine/Brownian_Motion/__init__.py
python_backtesting_engine/Brownian_Motion/brownian.py
python_backtesting_engine/Brownian_Motion/config.py
python_backtesting_engine/Coinbase_Fetcher/FetchCoinbaseData.py
python_backtesting_engine/Coinbase_Fetcher/__init__.py
python_backtesting_engine-4.0.8.dist-info/LICENSE
python_backtesting_engine-4.0.8.dist-info/METADATA
python_backtesting_engine-4.0.8.dist-info/WHEEL
python_backtesting_engine-4.0.8.dist-info/top_level.txt
python_backtesting_engine-4.0.8.dist-info/RECORD
