Metadata-Version: 2.1
Name: python-backtesting-engine
Version: 4.0.8
Summary: Backtest your own algo, fetch Coinbase data, and generate Brownian data
Home-page: https://github.com/michael-vitucci3/BacktestingEngine
Author: mike
Author-email: Michael Vitucci <author@example.com>
License: GNU GENERAL PUBLIC LICENSE
Project-URL: Homepage, https://github.com/michael-vitucci3/BacktestingEngine
Classifier: Programming Language :: Python
Classifier: License :: OSI Approved :: MIT License
Classifier: Operating System :: OS Independent
Requires-Python: >=3.6
License-File: LICENSE
Requires-Dist: setuptools
Requires-Dist: matplotlib
Requires-Dist: numpy
Requires-Dist: pandas
Requires-Dist: scipy
Requires-Dist: requests
Requires-Dist: PyQt5
